plugpack/__init__.py
plugpack/module/__init__.py
plugpack/module/errors.py
plugpack/module/module.py
plugpack/module/module_printer.py
plugpack/module/pipeline.py
plugpack/module/mixin/__init__.py
plugpack/module/mixin/_base.py
plugpack/module/mixin/async_open.py
plugpack/module/mixin/doc.py
plugpack/module/mixin/logger.py
plugpack/module/mixin/open.py
plugpack/module/mixin/version.py
plugpack/package/__init__.py
plugpack/package/package_utils.py
plugpack/regex/__init__.py
plugpack/regex/access_filter.py
plugpack/system/__init__.py
plugpack/system/environ.py
plugpack/system/path_context.py
plugpack-0.1.0.dist-info/LICENSE
plugpack-0.1.0.dist-info/METADATA
plugpack-0.1.0.dist-info/WHEEL
plugpack-0.1.0.dist-info/top_level.txt
plugpack-0.1.0.dist-info/RECORD
